django_imperavi_redactor/__init__.py
django_imperavi_redactor/fields.py
django_imperavi_redactor/forms.py
django_imperavi_redactor/handlers.py
django_imperavi_redactor/static/redactor/init.js
django_imperavi_redactor/static/redactor/langs/en.js
django_imperavi_redactor/static/redactor/langs/ru.js
django_imperavi_redactor/static/redactor/override-redactor.css
django_imperavi_redactor/static/redactor/plugins/alignment/alignment.js
django_imperavi_redactor/static/redactor/plugins/counter/counter.js
django_imperavi_redactor/static/redactor/plugins/filemanager/filemanager.js
django_imperavi_redactor/static/redactor/plugins/fontcolor/fontcolor.js
django_imperavi_redactor/static/redactor/plugins/fontsize/fontsize.js
django_imperavi_redactor/static/redactor/plugins/fullscreen/fullscreen.js
django_imperavi_redactor/static/redactor/plugins/glvrdplugin/glvrdplugin.css
django_imperavi_redactor/static/redactor/plugins/glvrdplugin/glvrdplugin.js
django_imperavi_redactor/static/redactor/plugins/imagelink/imagelink.js
django_imperavi_redactor/static/redactor/plugins/imagemanager/imagemanager.js
django_imperavi_redactor/static/redactor/plugins/inlinestyle/inlinestyle.js
django_imperavi_redactor/static/redactor/plugins/properties/properties.js
django_imperavi_redactor/static/redactor/plugins/quote/quote.css
django_imperavi_redactor/static/redactor/plugins/quote/quote.js
django_imperavi_redactor/static/redactor/plugins/specialchars/specialchars.js
django_imperavi_redactor/static/redactor/plugins/specialtext/specialtext.css
django_imperavi_redactor/static/redactor/plugins/specialtext/specialtext.js
django_imperavi_redactor/static/redactor/plugins/table/table.js
django_imperavi_redactor/static/redactor/plugins/video/video.js
django_imperavi_redactor/static/redactor/plugins/widget/widget.js
django_imperavi_redactor/tests.py
django_imperavi_redactor/urls.py
django_imperavi_redactor/utils.py
django_imperavi_redactor/views.py
django_imperavi_redactor/widgets.py
django_imperavi_redactor-0.0.2.dist-info/LICENSE
django_imperavi_redactor-0.0.2.dist-info/WHEEL
django_imperavi_redactor-0.0.2.dist-info/METADATA
django_imperavi_redactor-0.0.2.dist-info/RECORD
