Metadata-Version: 2.1
Name: django-imperavi-redactor
Version: 0.0.2
Summary: Django wrapper for use imperavi redactor.
Home-page: https://github.com/brogency/django-imperavi-redactor
License: MIT
Keywords: django,imperavi,wysiwyg,redactor,editor
Author: Dmitry Bastrikin
Author-email: dima.bastrikin@bro.agency
Requires-Python: >=3.5,<4.0
Classifier: License :: OSI Approved :: MIT License
Classifier: Programming Language :: Python :: 3
Classifier: Programming Language :: Python :: 3.5
Classifier: Programming Language :: Python :: 3.6
Classifier: Programming Language :: Python :: 3.7
Requires-Dist: django (>=1.11,<3.0)
Project-URL: Repository, https://github.com/brogency/django-imperavi-redactor
